prepr/__init__.py
prepr/main.py
prepr/models.py
prepr/types.py
prepr/utils.py
prepr-0.0.7.dist-info/LICENSE
prepr-0.0.7.dist-info/METADATA
prepr-0.0.7.dist-info/WHEEL
prepr-0.0.7.dist-info/top_level.txt
prepr-0.0.7.dist-info/RECORD
