Metadata-Version: 2.1
Name: prepr
Version: 0.0.7
Summary: A system for creating pretty class representations
Author-email: "Tanner B. Corcoran" <tannerbcorcoran@gmail.com>
Project-URL: Homepage, https://github.com/tanrbobanr/prepr
Project-URL: Documentation, https://github.com/tanrbobanr/prepr/blob/main/README.md
Classifier: Programming Language :: Python :: 3
Classifier: License :: OSI Approved :: MIT License
Classifier: Operating System :: OS Independent
Requires-Python: >=3.6
License-File: LICENSE
